<?xml version='1.0' encoding='UTF-8'?>
<AM-DA50:publication xmlns:xsi="http://www.w3.org/2001/XMLSchema-instance" xmlns:AM-DA50="https://shab.ch/kabda/AM-DA50-export" xsi:schemaLocation="https://shab.ch/kabda/AM-DA50-export https://amtsblattportal.ch/api/v1/schemas/kabda/1.21/AM-DA50-export.xsd">
<meta>
  <id>a884ebf5-482c-425a-a958-2d9698737b0f</id>
  <rubric>AM-DA</rubric>
  <subRubric>AM-DA50</subRubric>
  <language>de</language>
  <registrationOffice>
    <id>48667d86-d29c-11ec-89c4-04505600900b</id>
    <displayName>Gemeinde Ostermundigen - Hochbau</displayName>
    <street>Bernstrasse</street>
    <streetNumber>65D</streetNumber>
    <swissZipCode>3072</swissZipCode>
    <town>Ostermundigen</town>
    <containsPostOfficeBox>false</containsPostOfficeBox>
    <municipalityId>363</municipalityId>
  </registrationOffice>
  <publicationNumber>AM-DA50-0000001077</publicationNumber>
  <publicationState>PUBLISHED</publicationState>
  <publicationDate>2024-05-15</publicationDate>
  <expirationDate>2025-05-15</expirationDate>
  <primaryTenantCode>kabda</primaryTenantCode>
  <cantons>BE</cantons>
  <title>
    <de>Baugesuch – Gedeckter Autounterstand (Carport), Ostermundigen</de>
    <en>AM-DA50-0000001077</en>
    <it>AM-DA50-0000001077</it>
    <fr>Demande d'autorisation de construire – Gedeckter Autounterstand (Carport), Ostermundigen</fr>
  </title>
</meta>
<content>
  <controls>
    <translation>false</translation>
    <apiImport>false</apiImport>
  </controls>
  <regOfficeSignature>
    <img>KO_363</img>
  </regOfficeSignature>
  <action>
    <key>notice</key>
  </action>
  <businessCase>
    <key>constructionProject</key>
    <primary>
      <element>
        <key>constructionProjectTitle</key>
        <valueType>text</valueType>
        <valueText>
          <term>
            <de>Gedeckter Autounterstand (Carport)</de>
          </term>
        </valueText>
      </element>
    </primary>
    <secondary>
      <element>
        <key>projectAddress</key>
        <valueType>address</valueType>
        <term>
          <de>Adresse des Bauprojekts</de>
          <fr>Adresse du projet de construction</fr>
        </term>
        <delimiterTitle> – </delimiterTitle>
        <customTerm>false</customTerm>
        <enumeration/>
        <valueText/>
        <address>
          <street>Dammweg</street>
          <houseNumber>9</houseNumber>
          <swissZipCode>3072</swissZipCode>
          <town>Ostermundigen</town>
        </address>
        <subject>
          <naturalPerson>
            <residence/>
          </naturalPerson>
        </subject>
      </element>
    </secondary>
    <secondary>
      <element>
        <key>parcel</key>
        <valueType>textNeutral</valueType>
        <term>
          <de>Parzelle</de>
          <fr>Parcelle</fr>
        </term>
        <delimiterTitle> – </delimiterTitle>
        <customTerm>false</customTerm>
        <enumeration/>
        <valueText/>
        <valueTextNeutral>1495</valueTextNeutral>
        <subject>
          <naturalPerson>
            <residence/>
          </naturalPerson>
        </subject>
      </element>
    </secondary>
    <secondary>
      <element>
        <key>zone</key>
        <valueType>text</valueType>
        <term>
          <de>Zone</de>
          <fr>Zone</fr>
        </term>
        <delimiterTitle> – </delimiterTitle>
        <customTerm>false</customTerm>
        <enumeration/>
        <valueText>
          <term>
            <de>Wohnzone 3</de>
          </term>
        </valueText>
        <subject>
          <naturalPerson>
            <residence/>
          </naturalPerson>
        </subject>
      </element>
    </secondary>
    <secondary>
      <element>
        <key>exceptions</key>
        <valueType>text</valueType>
        <term>
          <de>Ausnahmen</de>
          <fr>Dérogations</fr>
        </term>
        <delimiterTitle> – </delimiterTitle>
        <customTerm>false</customTerm>
        <enumeration/>
        <valueText>
          <term>
            <de>Bauen in der Bauverbotszone (Art. 81 Abs. 2 SG und Art. 29 GBR 93 i.V.m. Art. 28 BauG)</de>
          </term>
        </valueText>
        <subject>
          <naturalPerson>
            <residence/>
          </naturalPerson>
        </subject>
      </element>
    </secondary>
  </businessCase>
  <reaction>
    <element>
      <legalRemedy>
        <de>&lt;p>&lt;b>Auflage- und Einsprachefrist: bis und mit 14. Juni 2024&lt;/b>&lt;/p>&lt;p>Es wird auf die Gesuchsakten. Diese liegen bei der Abteilung Hochbau während den Büroöffnungszeiten auf oder sind online einsehbar.&lt;/p>&lt;p>Allfällige Einsprachen, Rechtsverwahrungen und Lastenausgleichsansprüche sind schriftlich, im Doppel, und begründet innerhalb der Einsprachefrist einzureichen. Bei Kollektiveinsprachen und vervielfältigten oder weitgehend identischen Einsprachen ist anzugeben, wer befugt ist, die Einsprachegruppe rechtsverbindlich zu vertreten. &lt;/p>&lt;div>&lt;div>&lt;/div>&lt;/div></de>
      </legalRemedy>
      <contact>
        <de>&lt;div>&lt;div>Gemeinde Ostermundigen - Hochbau&lt;br/>Bernstrasse 65D &lt;br/>3072 Ostermundigen&lt;/div>&lt;/div></de>
      </contact>
      <deadline>
        <selectType>date</selectType>
        <term>
          <de>Frist</de>
        </term>
        <date>2024-06-14</date>
      </deadline>
    </element>
  </reaction>
  <localization>
    <municipalityId>
      <key>363</key>
      <term>
        <de>Ostermundigen</de>
        <fr>Ostermundigen</fr>
      </term>
    </municipalityId>
  </localization>
</content>
</AM-DA50:publication>